CHANGES
LICENSE
README.txt
setup.cfg
setup.py
iw/__init__.py
iw.quality.egg-info/PKG-INFO
iw.quality.egg-info/SOURCES.txt
iw.quality.egg-info/dependency_links.txt
iw.quality.egg-info/entry_points.txt
iw.quality.egg-info/namespace_packages.txt
iw.quality.egg-info/not-zip-safe
iw.quality.egg-info/requires.txt
iw.quality.egg-info/top_level.txt
iw/quality/README.txt
iw/quality/__init__.py
iw/quality/decorators.py
iw/quality/levenshtein.py
iw/quality/visitor.py
iw/quality/docs/README.txt
iw/quality/doctests/decorators.txt
iw/quality/doctests/levenshtein.txt
iw/quality/doctests/visitor.txt
iw/quality/tests/__init__.py
iw/quality/tests/test_qualitydocs.py
iw/quality/tests/data/source1.py
iw/quality/tests/data/source2.py
