Metadata-Version: 1.0
Name: iw.quality
Version: 0.1dev-r6462
Summary: QA Tools
Home-page: http://ingeniweb.svn.sourceforge.net/viewvc/ingeniweb/iw.quality
Author: Ingeniweb
Author-email: support@ingeniweb.com
License: GPL
Keywords: qa
Platform: UNKNOWN
Classifier: Programming Language :: Python
Classifier: Topic :: Software Development :: Libraries :: Python Modules
